passagemath_flint/__init__.py
passagemath_flint.libs/libflint-5b7728ce.so.22.0.0
passagemath_flint.libs/libgf2x-fbd36f80.so.3.0.0
passagemath_flint.libs/libgfortran-e1b7dfc8.so.5.0.0
passagemath_flint.libs/libgmp-93ebf16a.so.10.5.0
passagemath_flint.libs/libgsl-81284b87.so.28.0.0
passagemath_flint.libs/libmpfi-cadd719a.so.0.0.0
passagemath_flint.libs/libmpfr-3f4cfc34.so.6.2.2
passagemath_flint.libs/libntl-1bc30f7e.so.45.0.0
passagemath_flint.libs/libopenblasp-r0-c90e614e.3.29.so
sage/all__sagemath_flint.py
sage/combinat/all__sagemath_flint.py
sage/combinat/posets/all__sagemath_flint.py
sage/combinat/posets/hasse_cython_flint.cpython-314t-aarch64-linux-gnu.so
sage/combinat/posets/hasse_cython_flint.pyx
sage/data_structures/all__sagemath_flint.py
sage/data_structures/bounded_integer_sequences.cpython-314t-aarch64-linux-gnu.so
sage/data_structures/bounded_integer_sequences.pxd
sage/data_structures/bounded_integer_sequences.pyx
sage/graphs/all__sagemath_flint.py
sage/graphs/chrompoly.cpython-314t-aarch64-linux-gnu.so
sage/graphs/chrompoly.pyx
sage/graphs/matchpoly.cpython-314t-aarch64-linux-gnu.so
sage/graphs/matchpoly.pyx
sage/libs/all__sagemath_flint.py
sage/libs/arb/__init__.py
sage/libs/arb/acb.pxd
sage/libs/arb/acb_calc.pxd
sage/libs/arb/acb_elliptic.pxd
sage/libs/arb/acb_hypgeom.pxd
sage/libs/arb/acb_mat.pxd
sage/libs/arb/acb_modular.pxd
sage/libs/arb/acb_poly.pxd
sage/libs/arb/arb.pxd
sage/libs/arb/arb_fmpz_poly.pxd
sage/libs/arb/arb_hypgeom.pxd
sage/libs/arb/arb_wrap.h
sage/libs/arb/arf.pxd
sage/libs/arb/arith.cpython-314t-aarch64-linux-gnu.so
sage/libs/arb/arith.pyx
sage/libs/arb/bernoulli.pxd
sage/libs/arb/mag.pxd
sage/libs/arb/types.pxd
sage/libs/flint/__init__.py
sage/libs/flint/acb.pxd
sage/libs/flint/acb_calc.pxd
sage/libs/flint/acb_dft.pxd
sage/libs/flint/acb_dirichlet.pxd
sage/libs/flint/acb_elliptic.pxd
sage/libs/flint/acb_hypgeom.pxd
sage/libs/flint/acb_macros.pxd
sage/libs/flint/acb_mat.pxd
passagemath_flint-10.6.43.dist-info/METADATA
passagemath_flint-10.6.43.dist-info/WHEEL
passagemath_flint-10.6.43.dist-info/top_level.txt
passagemath_flint-10.6.43.dist-info/RECORD
passagemath_flint-10.6.43.dist-info/sboms/auditwheel.cdx.json
